[
  {
    "name": "empty_p1",
    "current_player": 1,
    "grid": [
      0,
      0,
      0,
      0,
      0,
      0,
      0,
      0,
      0,
      0,
      0,
      0,
      0,
      0,
      0,
      0,
      0,
      0,
      0,
      0,
      0,
      0,
      0,
      0,
      0,
      0,
      0,
      0,
      0,
      0,
      0,
      0,
      0,
      0,
      0,
      0,
      0,
      0,
      0,
      0,
      0,
      0
    ],
    "dqn_q_values": [
      0.7212870717048645,
      0.7410361766815186,
      0.7827531695365906,
      0.7983705401420593,
      0.7867278456687927,
      0.6836851239204407,
      0.6598629355430603
    ],
    "dqn_chosen_move": 3,
    "ppo_logits": [
      -1.7346194982528687,
      -1.2877135276794434,
      -0.4718247652053833,
      -1.610664963722229,
      10.750865936279297,
      -2.8891305923461914,
      -6.3371782302856445
    ],
    "ppo_chosen_move": 4
  },
  {
    "name": "empty_p2",
    "current_player": 2,
    "grid": [
      0,
      0,
      0,
      0,
      0,
      0,
      0,
      0,
      0,
      0,
      0,
      0,
      0,
      0,
      0,
      0,
      0,
      0,
      0,
      0,
      0,
      0,
      0,
      0,
      0,
      0,
      0,
      0,
      0,
      0,
      0,
      0,
      0,
      0,
      0,
      0,
      0,
      0,
      0,
      0,
      0,
      0
    ],
    "dqn_q_values": [
      0.7212870717048645,
      0.7410361766815186,
      0.7827531695365906,
      0.7983705401420593,
      0.7867278456687927,
      0.6836851239204407,
      0.6598629355430603
    ],
    "dqn_chosen_move": 3,
    "ppo_logits": [
      -1.7346194982528687,
      -1.2877135276794434,
      -0.4718247652053833,
      -1.610664963722229,
      10.750865936279297,
      -2.8891305923461914,
      -6.3371782302856445
    ],
    "ppo_chosen_move": 4
  },
  {
    "name": "center_p2_to_move",
    "current_player": 2,
    "grid": [
      0,
      0,
      0,
      0,
      0,
      0,
      0,
      0,
      0,
      0,
      0,
      0,
      0,
      0,
      0,
      0,
      0,
      0,
      0,
      0,
      0,
      0,
      0,
      0,
      0,
      0,
      0,
      0,
      0,
      0,
      0,
      0,
      0,
      0,
      0,
      0,
      0,
      0,
      1,
      0,
      0,
      0
    ],
    "dqn_q_values": [
      0.7099064588546753,
      0.9361457228660583,
      0.6854119300842285,
      0.8992365598678589,
      0.7605477571487427,
      0.8590179681777954,
      0.5889810919761658
    ],
    "dqn_chosen_move": 1,
    "ppo_logits": [
      5.435666084289551,
      4.5486345291137695,
      -1.193118691444397,
      -5.690547466278076,
      3.879788398742676,
      -2.9534060955047607,
      -4.836641311645508
    ],
    "ppo_chosen_move": 0
  },
  {
    "name": "random_seed1_moves5",
    "current_player": 2,
    "grid": [
      0,
      0,
      0,
      0,
      0,
      0,
      0,
      0,
      0,
      0,
      0,
      0,
      0,
      0,
      0,
      0,
      0,
      0,
      0,
      0,
      0,
      0,
      0,
      0,
      0,
      0,
      0,
      0,
      0,
      0,
      0,
      2,
      0,
      0,
      0,
      1,
      0,
      0,
      1,
      0,
      1,
      2
    ],
    "dqn_q_values": [
      0.8100073337554932,
      0.80238276720047,
      0.8995445966720581,
      0.7336541414260864,
      0.7866454124450684,
      0.6543492078781128,
      0.674373209476471
    ],
    "dqn_chosen_move": 2,
    "ppo_logits": [
      0.564210057258606,
      -1.1391019821166992,
      4.7762250900268555,
      -9.500157356262207,
      12.170024871826172,
      -6.218138694763184,
      -5.39722204208374
    ],
    "ppo_chosen_move": 4
  },
  {
    "name": "random_seed2_moves10",
    "current_player": 1,
    "grid": [
      0,
      0,
      0,
      0,
      0,
      0,
      0,
      0,
      0,
      0,
      0,
      0,
      0,
      0,
      0,
      0,
      0,
      0,
      0,
      0,
      0,
      0,
      0,
      1,
      0,
      0,
      0,
      0,
      2,
      0,
      1,
      0,
      0,
      2,
      0,
      1,
      2,
      2,
      1,
      2,
      1,
      0
    ],
    "dqn_q_values": [
      0.4492635130882263,
      1.0161633491516113,
      1.05599045753479,
      0.6584683656692505,
      0.6730604767799377,
      0.724355161190033,
      0.870553731918335
    ],
    "dqn_chosen_move": 2,
    "ppo_logits": [
      -6.2995147705078125,
      13.800833702087402,
      -7.991342544555664,
      2.17018723487854,
      3.80672550201416,
      -3.5048985481262207,
      -4.731012344360352
    ],
    "ppo_chosen_move": 1
  },
  {
    "name": "random_seed3_moves15",
    "current_player": 2,
    "grid": [
      0,
      0,
      0,
      0,
      0,
      0,
      0,
      0,
      0,
      0,
      0,
      0,
      0,
      0,
      0,
      1,
      0,
      0,
      0,
      0,
      0,
      2,
      1,
      0,
      0,
      0,
      0,
      0,
      1,
      2,
      0,
      2,
      1,
      2,
      0,
      2,
      1,
      1,
      2,
      2,
      1,
      1
    ],
    "dqn_q_values": [
      0.6487219929695129,
      0.7878739237785339,
      0.5753586888313293,
      0.8365065455436707,
      0.6569541692733765,
      0.4433302879333496,
      0.37291041016578674
    ],
    "dqn_chosen_move": 3,
    "ppo_logits": [
      0.05415244773030281,
      6.748534202575684,
      -5.020312786102295,
      -2.2046046257019043,
      8.450671195983887,
      -5.084210395812988,
      -2.9132440090179443
    ],
    "ppo_chosen_move": 4
  },
  {
    "name": "random_seed4_moves20",
    "current_player": 1,
    "grid": [
      0,
      0,
      0,
      0,
      0,
      0,
      2,
      0,
      0,
      0,
      0,
      0,
      0,
      1,
      0,
      0,
      0,
      0,
      1,
      0,
      2,
      0,
      1,
      0,
      2,
      1,
      0,
      1,
      0,
      2,
      0,
      1,
      1,
      2,
      1,
      2,
      1,
      2,
      2,
      2,
      1,
      2
    ],
    "dqn_q_values": [
      0.2504303455352783,
      0.27579110860824585,
      0.4286770820617676,
      0.4692709147930145,
      0.7115241289138794,
      0.3700268864631653,
      -0.026650220155715942
    ],
    "dqn_chosen_move": 4,
    "ppo_logits": [
      -3.8979804515838623,
      -3.4847664833068848,
      -2.330127477645874,
      6.45334005355835,
      -1.666861891746521,
      14.508631706237793,
      -17.60687255859375
    ],
    "ppo_chosen_move": 5
  },
  {
    "name": "random_seed5_moves25",
    "current_player": 2,
    "grid": [
      2,
      0,
      1,
      0,
      0,
      0,
      0,
      1,
      0,
      2,
      0,
      0,
      0,
      0,
      2,
      0,
      1,
      0,
      0,
      0,
      0,
      1,
      0,
      2,
      1,
      2,
      1,
      0,
      2,
      1,
      2,
      2,
      1,
      2,
      2,
      1,
      1,
      2,
      1,
      1,
      2,
      1
    ],
    "dqn_q_values": [
      0.062020570039749146,
      0.2509583532810211,
      -0.1607632339000702,
      0.47902706265449524,
      0.5786527395248413,
      0.3375832736492157,
      -0.012496426701545715
    ],
    "dqn_chosen_move": 4,
    "ppo_logits": [
      -12.238773345947266,
      18.420623779296875,
      -16.240894317626953,
      3.05795955657959,
      -1.320422649383545,
      5.551852703094482,
      0.4603142738342285
    ],
    "ppo_chosen_move": 1
  }
]